biofiles/__init__.py
biofiles/bam.py
biofiles/common.py
biofiles/fai.py
biofiles/fasta.py
biofiles/gff.py
biofiles/gtf.py
biofiles/repeatmasker.py
biofiles/dialects/__init__.py
biofiles/dialects/detector.py
biofiles/dialects/gencode.py
biofiles/dialects/genomic_base.py
biofiles/dialects/refseq.py
biofiles/dialects/stringtie.py
biofiles/types/__init__.py
biofiles/types/alignment.py
biofiles/types/feature.py
biofiles/types/repeat.py
biofiles/types/sequence.py
biofiles/utility/__init__.py
biofiles/utility/cli.py
biofiles/utility/feature.py
biofiles-0.1.5.dist-info/licenses/LICENSE
biofiles-0.1.5.dist-info/METADATA
biofiles-0.1.5.dist-info/WHEEL
biofiles-0.1.5.dist-info/top_level.txt
biofiles-0.1.5.dist-info/RECORD
