Metadata-Version: 2.4
Name: biofiles
Version: 0.1.5
Summary: Pure-Python, zero-dependency collection of bioinformatics-related file readers and writers
Author-email: Tigran Saluev <tigran@saluev.com>
Maintainer-email: Tigran Saluev <tigran@saluev.com>
License: MIT License
Project-URL: Homepage, https://github.com/Saluev/biofiles
Classifier: Programming Language :: Python :: 3
Classifier: License :: OSI Approved :: MIT License
Classifier: Operating System :: OS Independent
Classifier: Programming Language :: Python :: 3.11
Classifier: Programming Language :: Python :: 3.12
Requires-Python: >=3.10
License-File: LICENSE
Dynamic: license-file
